MANIFEST.in
README.txt
setup.cfg
setup.py
docs/HISTORY.txt
docs/INSTALL.txt
docs/LICENSE.GPL
docs/LICENSE.txt
sc/__init__.py
sc.paster.buildout.egg-info/PKG-INFO
sc.paster.buildout.egg-info/SOURCES.txt
sc.paster.buildout.egg-info/dependency_links.txt
sc.paster.buildout.egg-info/entry_points.txt
sc.paster.buildout.egg-info/namespace_packages.txt
sc.paster.buildout.egg-info/not-zip-safe
sc.paster.buildout.egg-info/requires.txt
sc.paster.buildout.egg-info/top_level.txt
sc/paster/__init__.py
sc/paster/buildout/__init__.py
sc/paster/buildout/sc_buildout.py
sc/paster/buildout/docs/sc_buildout.txt
sc/paster/buildout/templates/sc_buildout/README.txt
sc/paster/buildout/templates/sc_buildout/base.cfg_tmpl
sc/paster/buildout/templates/sc_buildout/bootstrap.py
sc/paster/buildout/templates/sc_buildout/desenvolvimento.cfg_tmpl
sc/paster/buildout/templates/sc_buildout/homologa.cfg_tmpl
sc/paster/buildout/templates/sc_buildout/producao.cfg_tmpl
sc/paster/buildout/templates/sc_buildout/sources.cfg_tmpl
sc/paster/buildout/templates/sc_buildout/etc/logrotate.conf.tmpl
sc/paster/buildout/templates/sc_buildout/products/README.txt
sc/paster/buildout/templates/sc_buildout/src/README.txt
sc/paster/buildout/templates/sc_buildout/var/README.txt
sc/paster/buildout/tests/__init__.py
sc/paster/buildout/tests/test_templates.py