Metadata-Version: 1.0
Name: sc.paster.buildout
Version: 0.7
Summary: Simples Consultoria's buildout skeleton for Plone portals.
Home-page: http://www.simplesconsultoria.com.br/
Author: Erico Andrei
Author-email: erico@simplesconsultoria.com.br
License: GPL
Keywords: web zope plone development simples_consultoria
Platform: UNKNOWN
Classifier: Programming Language :: Python
Classifier: Topic :: Software Development :: Libraries :: Python Modules
